[
  {
    "videoId": "sUn3RCRxCh0",
    "meta": {
      "channelName": "제주해오름부동산",
      "videoTitle": "제주 최고의 표선 IB 학군, 시내인프라 10분컷 신축주택 매매",
      "regionHint": "서귀포시 표선면",
      "description": "제주 최고의 IB 학군과 10분 컷 표선 시내 인프라를 모두 품은 세화리의 142평 단층 전원주택 제목 : 제주 표선면 세화리 신축단독주택 ..."
    },
    "truth": {
      "priceManwon": 46000,
      "areaPyeong": 142,
      "region": "서귀포시 표선면",
      "zoning": null,
      "propertyType": "전원주택",
      "dealType": "매매"
    }
  },
  {
    "videoId": "0_Krot_A8Io",
    "meta": {
      "channelName": "제주네모부동산",
      "videoTitle": "A home I put 470 million won into, selling for 350 million won because of my dog: Island Hill woo...",
      "regionHint": "",
      "description": "This is Jeju Nemo Real Estate.\n\nThis property was listed a while ago for 390 million won, but the price has now been lowered ..."
    },
    "truth": {
      "priceManwon": 35000,
      "areaPyeong": null,
      "region": "서귀포시 대정읍",
      "zoning": null,
      "propertyType": "빌라",
      "dealType": "매매"
    }
  },
  {
    "videoId": "ahkqMKijMks",
    "meta": {
      "channelName": "제주네모부동산",
      "videoTitle": "[제주 주택 급매] 서귀포 회수동 바다 한라산조망, 14억에서 8억대로! 집에 뭔 일 있나?",
      "regionHint": "",
      "description": "제주네모부동산 독점 매물입니다. 제주 서귀포 중산간 회수동에 나온 급매물 주택입니다. 제주도 자연환경에 최적화 된 집 입니다."
    },
    "truth": {
      "priceManwon": 85000,
      "areaPyeong": null,
      "region": "서귀포시 회수동",
      "zoning": null,
      "propertyType": "전원주택",
      "dealType": "매매"
    }
  },
  {
    "videoId": "qwE7VES0gtQ",
    "meta": {
      "channelName": "제주도 슬기로운 내집마련 제일하우스",
      "videoTitle": "A-198)제주 서쪽 가성비 끝판왕! 개별등기 신축 전원주택 분양 제주 2억5천 신축 전원주택! 100평 대지·개별등기·영어교육도시 15분  단독주택 분양",
      "regionHint": "",
      "description": "매물문의 제일하우스 : 010-2425-4311 안녕하세요 제주도 부동산 전문채널 제일하우스 입니다. 제주도 부동산 정보를 발빠르고 ..."
    },
    "truth": {
      "priceManwon": 25000,
      "areaPyeong": 100,
      "region": "제주시 한경면",
      "zoning": null,
      "propertyType": "전원주택",
      "dealType": "매매"
    }
  },
  {
    "videoId": "i4WovCZcP8Q",
    "meta": {
      "channelName": "알밤부동산",
      "videoTitle": "(Price Drop) Luxury House in Jeju Island: Highly Recommended as a Second Home Near Hamdeok Beach",
      "regionHint": "",
      "description": "Urgent Sale Price: 1 Billion KRW\n\nConsultation & Visit Reservations: 010-5454-2540 ..."
    },
    "truth": {
      "priceManwon": 100000,
      "areaPyeong": null,
      "region": "제주시 조천읍",
      "zoning": null,
      "propertyType": "단독주택",
      "dealType": "매매"
    }
  },
  {
    "videoId": "ifzePbpYkhQ",
    "meta": {
      "channelName": "제주 부동산 25시 ",
      "videoTitle": "[매물번호0637]애월해안도로 접 영구조망 환상적인바다뷰를 품은 상가주택 매물",
      "regionHint": "제주시 애월읍",
      "description": "매물정보○ 자연녹지 건폐율20%용적율80% 대지 351m² [약 107평] 건물 196m² 상가와주택[바다뷰북향] 매매가 12억[빠른거래시 ..."
    },
    "truth": {
      "priceManwon": 120000,
      "areaPyeong": 107,
      "region": "제주시 애월읍",
      "zoning": "자연녹지지역",
      "propertyType": "상가주택",
      "dealType": "매매"
    }
  },
  {
    "videoId": "1iBTGWYgKRc",
    "meta": {
      "channelName": "제주도다올레공인중개사",
      "videoTitle": "제주시 애월읍 곽지리 해수욕장 코앞 빌라 전용21평 1억도안됨 010 4436 0401 #제주도 부동산 토지 매매 #급매물",
      "regionHint": "제주시 애월읍",
      "description": "물건내용 □ 다올레공인중개사사무소 http://www.daolle.com 등록번호 : 50110 2022 00122 제주시 한천로 65 대표 김용만 010 4436 ..."
    },
    "truth": {
      "priceManwon": 9000,
      "areaPyeong": 21,
      "region": "제주시 애월읍",
      "zoning": "1종일반주거지역",
      "propertyType": "빌라",
      "dealType": "매매"
    }
  },
  {
    "videoId": "Yuj9vCB-7yw",
    "meta": {
      "channelName": "채널 탐라집",
      "videoTitle": "[가격인하]제주시 애월읍 조용한 시골마을의 소박한 즐거움이 있는 구옥리모델링 감성단독주택",
      "regionHint": "제주시 애월읍",
      "description": "애월읍 봉성리에 위치한 조용한 시골마을안의 농어촌민박으로 운영중인 제주감성 리모델링 단독주택 입니다. ------- [No_11145] ..."
    },
    "truth": {
      "priceManwon": 53000,
      "areaPyeong": null,
      "region": "제주시 애월읍",
      "zoning": "관리지역",
      "propertyType": "단독주택",
      "dealType": "매매"
    }
  },
  {
    "videoId": "RXzQPTCmOxY",
    "meta": {
      "channelName": "제주도 슬기로운 내집마련 제일하우스",
      "videoTitle": "A-194)가격 무너졌습니다! 애월 오션뷰 단독주택 제주 애월 단독주택이 2억대? 오션뷰에 1억 인하된 하가리 급매물 제주도부동산매매 제주도주택매매.",
      "regionHint": "제주시 애월읍",
      "description": "문의 : 제일하우스 010-2425-4311 오늘 소개해드릴 매물은 제주시 애월읍 하가리에 위치한 오션뷰 단독주택 급매물입니다."
    },
    "truth": {
      "priceManwon": 29000,
      "areaPyeong": null,
      "region": "제주시 애월읍",
      "zoning": null,
      "propertyType": "단독주택",
      "dealType": "매매"
    }
  },
  {
    "videoId": "SK-55ES3pb8",
    "meta": {
      "channelName": "제주도 슬기로운 내집마련 제일하우스",
      "videoTitle": "A-124)“제주 애월 오션뷰 단독주택 급급매! 2억 후반대 풀옵션 감성주택｜공항 30분 거리｜실내에서도 오션뷰 조망 가능#제주도부동산 ",
      "regionHint": "제주시 애월읍",
      "description": "오늘 보신 이 집, 지금 이 금액으로는 다시 못 만납니다. 실거주든 투자든, 놓치면 평생 후회할 애월 오션뷰 단독주택! 지금 바로 문의 ..."
    },
    "truth": {
      "priceManwon": 29000,
      "areaPyeong": null,
      "region": "제주시 애월읍",
      "zoning": null,
      "propertyType": "단독주택",
      "dealType": "매매"
    }
  },
  {
    "videoId": "DXO3HrXlHSc",
    "meta": {
      "channelName": "제주 부동산 25시 ",
      "videoTitle": "[매물번호0619] 먼바다뷰와 대중교통 위치와 입지  애월에 개별단층주택 6채 주인을 찾습니다",
      "regionHint": "제주시 애월읍",
      "description": "매물정보○ 3억5천 단층신축주택 분양 소개 바다뷰 (북향)의 단층 30평형대 라임스톤 고급주택 방2화장실2 조경과 시스템에어컨까지 ..."
    },
    "truth": {
      "priceManwon": 35000,
      "areaPyeong": 30,
      "region": "제주시 애월읍",
      "zoning": null,
      "propertyType": "단독주택",
      "dealType": "매매"
    }
  },
  {
    "videoId": "mzzEy8jtxfA",
    "meta": {
      "channelName": "탐나는 집 - 제주백방TV ",
      "videoTitle": "분양가보다 저렴한 제주 타운하우스 더퍼스트애월 남향 매매 / 애조로, 서부경찰서 옆 위치, 제주시 애월읍 상귀리 [탐나는집, 제주도부동산]",
      "regionHint": "제주시 애월읍",
      "description": "안녕하세요~! 제주 백방TV 제주 백방 부동산 최소장 입니다. 문의 : 010-2691-1898 (문자도 환영) 카카오톡 : freefana 매매 3억 9500 ..."
    },
    "truth": {
      "priceManwon": 39500,
      "areaPyeong": null,
      "region": "제주시 애월읍",
      "zoning": null,
      "propertyType": "빌라",
      "dealType": "매매"
    }
  },
  {
    "videoId": "F56HmS4yK0o",
    "meta": {
      "channelName": "알밤부동산",
      "videoTitle": "제주도 애월에서 소개해드리는 마당있는 전원주택 급매물 입니다.",
      "regionHint": "제주시 애월읍",
      "description": "급매가격 : 3억 ▷ 최초 3억 8천 (8천만원 인하) 상담 및 방문예약 : 010-5454-2540 ..."
    },
    "truth": {
      "priceManwon": 30000,
      "areaPyeong": null,
      "region": "제주시 애월읍",
      "zoning": null,
      "propertyType": "전원주택",
      "dealType": "매매"
    }
  },
  {
    "videoId": "LBZEagJrn2o",
    "meta": {
      "channelName": "제주소랑부동산 - 제주도 부동산의 모든 것",
      "videoTitle": "바다 영구조망 풀옵션의 제주도 조천 바닷가 바로 앞 단독주택. 감성 숙소 펜션 운영 가능",
      "regionHint": "제주시 조천읍",
      "description": "[매물번호 260305] 금액: 7억5천 풀옵션 (가격 협상에 최선을 다하겠습니다) 소재지: 제주시 조천읍 신촌리 (제주공항 차량 28분."
    },
    "truth": {
      "priceManwon": 75000,
      "areaPyeong": null,
      "region": "제주시 조천읍",
      "zoning": null,
      "propertyType": "단독주택",
      "dealType": "매매"
    }
  },
  {
    "videoId": "SWfUWJ3hFEk",
    "meta": {
      "channelName": "제주 부동산 25시 ",
      "videoTitle": "[매물번호0592]  조천읍 신촌리  비싸지만 탐나는 희소성 소형 대지   바닷가진짜바로앞#제주도부동산",
      "regionHint": "제주시 조천읍",
      "description": "매물정보○ 용도지역 : 2종일반주거지역 건폐율60%, 용적율250% 지목 : 대 면적 : 294m² *바다 바로 앞 희소성있는 토지 매매가 5억 ..."
    },
    "truth": {
      "priceManwon": 50000,
      "areaPyeong": 89,
      "region": "제주시 조천읍",
      "zoning": "2종일반주거지역",
      "propertyType": "토지",
      "dealType": "매매"
    }
  },
  {
    "videoId": "ERlz8qoMmB0",
    "meta": {
      "channelName": "채널 탐라집",
      "videoTitle": "제주시 조천읍 숲을 마주하며 휴식을 즐길수 있는 프라이빗한 고급 스테이 풀빌라 단독주택 매매",
      "regionHint": "제주시 조천읍",
      "description": "오늘 소개해 드릴 매물은 제주 동북부지역 조천읍 대흘리에 위치한 숲을 마주하며 휴식을 즐길수 있는 프라이빗한 고급 스테이 풀빌라 ..."
    },
    "truth": {
      "priceManwon": 150000,
      "areaPyeong": null,
      "region": "제주시 조천읍",
      "zoning": null,
      "propertyType": "단독주택",
      "dealType": "매매"
    }
  },
  {
    "videoId": "BMES84ZWveY",
    "meta": {
      "channelName": "제주도다올레공인중개사",
      "videoTitle": "Luxury Townhouse in Sinchon-ri, Jocheon-eup, Jeju City (58 Pyeong) - Under Half Price at 220 Mill...",
      "regionHint": "",
      "description": "■ Property Details\n\n■ Daolle Real Estate Agency http://www.daolle.com\n\nRegistration No.: 50110 2022 00122\n\n65, Hancheon-ro ..."
    },
    "truth": {
      "priceManwon": 23000,
      "areaPyeong": 58,
      "region": "제주시 조천읍",
      "zoning": null,
      "propertyType": "빌라",
      "dealType": "매매"
    }
  },
  {
    "videoId": "4jZvV-4v9hM",
    "meta": {
      "channelName": "제주도다올레공인중개사",
      "videoTitle": "[경매] 제주시 조천읍 신촌리 고급 타운하우스 대141평 지분 건78평 010 4436 0401 #제주도 부동산 토지 매매 #급매물",
      "regionHint": "제주시 조천읍",
      "description": "물건내용 □ 다올레공인중개사사무소 http://www.daolle.com 등록번호 : 50110 2022 00122 제주시 한천로 65 대표 김용만 010 4436 ..."
    },
    "truth": {
      "priceManwon": 22000,
      "areaPyeong": 78,
      "region": "제주시 조천읍",
      "zoning": null,
      "propertyType": "빌라",
      "dealType": "경매"
    }
  },
  {
    "videoId": "Q2YlP2N8bZ0",
    "meta": {
      "channelName": "제주도다올레공인중개사",
      "videoTitle": "제주시 조천읍 신흥리 바닷가 해안도로 635평 조절가능 급매 010 4436 0401 #제주도 부동산 토지 매매 #급매물",
      "regionHint": "제주시 조천읍",
      "description": "물건내용 □ 다올레공인중개사사무소 http://www.daolle.com 등록번호 : 50110 2022 00122 제주시 한천로 65 대표 김용만 010 4436 ..."
    },
    "truth": {
      "priceManwon": 127000,
      "areaPyeong": 635,
      "region": "제주시 조천읍",
      "zoning": null,
      "propertyType": "토지",
      "dealType": "매매"
    }
  },
  {
    "videoId": "KqOMxoz5HIc",
    "meta": {
      "channelName": "알밤부동산",
      "videoTitle": "Introducing a peaceful countryside house in Gangjeong-dong, Seogwipo city center.",
      "regionHint": "",
      "description": "Sale Price: 750 million KRW\n\nConsultation & Visit Reservations: 010-5454-2540 ..."
    },
    "truth": {
      "priceManwon": 75000,
      "areaPyeong": 48,
      "region": "서귀포시 강정동",
      "zoning": null,
      "propertyType": "단독주택",
      "dealType": "매매"
    }
  },
  {
    "videoId": "4H8DM6MbYhU",
    "meta": {
      "channelName": "제주 부동산 25시 ",
      "videoTitle": "[매물번호0554] 서귀포 이마트 종합운동장 관공서가까운 택지 단지 반값초급매물 대지 #제주도부동산",
      "regionHint": "",
      "description": "매물정보○ 용도지역 : 1종일반주거지역 건폐율60%, 용적율200% 지목 : 대 면적 : 317m² (96평) 바다뷰 쾌적한 택지지구 내 토지 모든 ..."
    },
    "truth": {
      "priceManwon": 25000,
      "areaPyeong": 96,
      "region": "서귀포시 법환동",
      "zoning": "1종일반주거지역",
      "propertyType": "토지",
      "dealType": "매매"
    }
  }
]
